odoo/addons/l10n_cl_etd_xerox/README.rst
odoo/addons/l10n_cl_etd_xerox/__init__.py
odoo/addons/l10n_cl_etd_xerox/__manifest__.py
odoo/addons/l10n_cl_etd_xerox/data/backend.acp.csv
odoo/addons/l10n_cl_etd_xerox/data/etd_document_invoice.xml
odoo/addons/l10n_cl_etd_xerox/data/etd_document_stock.xml
odoo/addons/l10n_cl_etd_xerox/data/etd_xerox_cron.xml
odoo/addons/l10n_cl_etd_xerox/i18n/es_CL.po
odoo/addons/l10n_cl_etd_xerox/i18n/l10n_cl_etd_xerox.pot
odoo/addons/l10n_cl_etd_xerox/models/__init__.py
odoo/addons/l10n_cl_etd_xerox/models/backend_acp.py
odoo/addons/l10n_cl_etd_xerox/models/etd_document.py
odoo/addons/l10n_cl_etd_xerox/models/etd_mixin.py
odoo/addons/l10n_cl_etd_xerox/readme/CONTRIBUTORS.rst
odoo/addons/l10n_cl_etd_xerox/readme/DESCRIPTION.rst
odoo/addons/l10n_cl_etd_xerox/static/description/icon.png
odoo/addons/l10n_cl_etd_xerox/static/description/index.html
odoo/addons/l10n_cl_etd_xerox/views/backend_acp.xml
odoo12_addon_l10n_cl_etd_xerox-12.0.1.0.2.dist-info/METADATA
odoo12_addon_l10n_cl_etd_xerox-12.0.1.0.2.dist-info/WHEEL
odoo12_addon_l10n_cl_etd_xerox-12.0.1.0.2.dist-info/top_level.txt
odoo12_addon_l10n_cl_etd_xerox-12.0.1.0.2.dist-info/RECORD
