Metadata-Version: 2.1
Name: odoo12-addon-l10n-cl-etd-xerox
Version: 12.0.1.0.2
Summary: Use Xerox electronic document communication.
Home-page: https://github.com/OCA/l10n-chile
Author: Open Source Integrators, Odoo Community Association (OCA)
Author-email: support@odoo-community.org
License: AGPL-3
Platform: UNKNOWN
Classifier: Programming Language :: Python
Classifier: Framework :: Odoo
Classifier: License :: OSI Approved :: GNU Affero General Public License v3
Classifier: Development Status :: 4 - Beta
Requires-Python: >=3.5
Requires-Dist: odoo12-addon-connector-acp-ftp
Requires-Dist: odoo12-addon-l10n-cl-etd-account
Requires-Dist: odoo12-addon-l10n-cl-etd-stock
Requires-Dist: odoo12-addon-l10n-cl-sii-activity
Requires-Dist: odoo12-addon-l10n-cl-sii-folio
Requires-Dist: odoo (<12.1dev,>=12.0a)
